[
  {
    "githubUrl": "https://github.com/doublesymmetry/react-native-track-player",
    "examples": [
      "https://github.com/doublesymmetry/react-native-track-player/tree/main/example"
    ],
    "images": [
      "https://raw.githubusercontent.com/doublesymmetry/react-native-track-player/dev/example/screenshots/ios-app.png",
      "https://raw.githubusercontent.com/doublesymmetry/react-native-track-player/dev/example/screenshots/ios-lockscreen.png",
      "https://raw.githubusercontent.com/doublesymmetry/react-native-track-player/dev/example/screenshots/android-app.png",
      "https://raw.githubusercontent.com/doublesymmetry/react-native-track-player/dev/example/screenshots/android-lockscreen.png",
      "https://raw.githubusercontent.com/doublesymmetry/react-native-track-player/dev/example/screenshots/android-notification.png"
    ],
    "ios": true,
    "android": true,
    "windows": true,
    "npmPkg": "react-native-track-player",
    "github": {
      "urls": {
        "repo": "https://github.com/doublesymmetry/react-native-track-player",
        "clone": "https://github.com/doublesymmetry/react-native-track-player.git",
        "homepage": "https://rntp.dev/"
      },
      "stats": {
        "hasIssues": true,
        "hasWiki": false,
        "hasPages": true,
        "hasDownloads": true,
        "hasTopics": true,
        "updatedAt": "2024-05-22T13:24:44Z",
        "createdAt": "2017-03-16T20:18:39Z",
        "pushedAt": "2024-05-19T10:13:39Z",
        "issues": 47,
        "subscribers": 50,
        "stars": 3150,
        "forks": 969
      },
      "name": "react-native-track-player",
      "fullName": "doublesymmetry/react-native-track-player",
      "description": "A fully fledged audio module created for music apps. Provides audio playback, external media controls, background mode and more!",
      "topics": [
        "react-native",
        "music-player",
        "music-library",
        "media-control",
        "android",
        "ios",
        "windows",
        "audio",
        "audio-library",
        "audio-player"
      ],
      "license": {
        "key": "apache-2.0",
        "name": "Apache License 2.0",
        "spdxId": "Apache-2.0",
        "url": "https://api.github.com/licenses/apache-2.0",
        "id": "MDc6TGljZW5zZTI="
      },
      "lastRelease": null,
      "hasTypes": true,
      "newArchitecture": false
    },
    "npm": {
      "downloads": 87330,
      "weekDownloads": 20851,
      "start": "2024-04-25",
      "end": "2024-05-24",
      "period": "month"
    },
    "topicSearchString": "react-native music-player music-library media-control android ios windows audio audio-library audio-player",
    "score": 88,
    "matchingScoreModifiers": [
      "Very popular",
      "Popular",
      "Recently updated"
    ],
    "popularity": -0.011,
    "category": [
      "music-player",
      "music-library",
      "media-control",
      "audio",
      "audio-library",
      "audio-player"
    ]
  }
]